pyramid_webassets/__init__.py
pyramid_webassets/tests/__init__.py
pyramid_webassets/tests/test_webassets.py
pyramid_webassets-0.10.dist-info/METADATA
pyramid_webassets-0.10.dist-info/RECORD
pyramid_webassets-0.10.dist-info/WHEEL
pyramid_webassets-0.10.dist-info/top_level.txt
