Metadata-Version: 2.1
Name: pyramid-webassets
Version: 0.10
Summary: pyramid_webassets
Home-page: http://github.com/sontek/pyramid_webassets
Author: John Anderson
Author-email: sontek@gmail.com
License: UNKNOWN
Keywords: web wsgi bfg pylons pyramid
Platform: UNKNOWN
Classifier: Programming Language :: Python
Classifier: Framework :: Pylons
Classifier: License :: OSI Approved :: MIT License
Classifier: Topic :: Internet :: WWW/HTTP
Classifier: Topic :: Internet :: WWW/HTTP :: WSGI :: Application
Provides-Extra: bundles-yaml
Requires-Dist: pyramid (>=1.4)
Requires-Dist: webassets (>=0.8)
Requires-Dist: zope.interface
Requires-Dist: six (>=1.4.1)
Provides-Extra: bundles-yaml
Requires-Dist: PyYAML (>=3.10); extra == 'bundles-yaml'
